light_character/__init__.py
light_character/cli.py
light_character/light_character.py
light_character/lighthouses/herbert/about.md
light_character/lighthouses/herbert/off.gif
light_character/lighthouses/herbert/on.gif
light_character/lighthouses/pier_vessels/about.md
light_character/lighthouses/pier_vessels/off.gif
light_character/lighthouses/pier_vessels/on.gif
light_character/lighthouses/rough_sea_ship/about.md
light_character/lighthouses/rough_sea_ship/off.gif
light_character/lighthouses/rough_sea_ship/on.gif
light_character-0.1.4.dist-info/AUTHORS.rst
light_character-0.1.4.dist-info/LICENSE
light_character-0.1.4.dist-info/METADATA
light_character-0.1.4.dist-info/WHEEL
light_character-0.1.4.dist-info/entry_points.txt
light_character-0.1.4.dist-info/top_level.txt
light_character-0.1.4.dist-info/RECORD
