Metadata-Version: 2.1
Name: light-character
Version: 0.1.4
Summary: Light Character illustrates light characteristics as found on charts and light lists
Home-page: https://github.com/paul-butcher/light_character
Author: Paul Butcher
Author-email: paul.butcher@gmail.com
License: MIT license
Keywords: light_character
Platform: UNKNOWN
Classifier: Development Status :: 2 - Pre-Alpha
Classifier: Intended Audience :: Developers
Classifier: License :: OSI Approved :: MIT License
Classifier: Natural Language :: English
Classifier: Programming Language :: Python :: 3
Classifier: Programming Language :: Python :: 3.6
Classifier: Programming Language :: Python :: 3.7
Classifier: Programming Language :: Python :: 3.8
Requires-Python: >=3.5
Requires-Dist: Pillow (==8.0.1)
